Metadata-Version: 2.4
Name: getstream-plugins-kokoro
Version: 0.1.0
Summary: Kokoro TTS plugin for GetStream
License-Expression: MIT
Requires-Python: >=3.10
Requires-Dist: getstream-plugins-common
Requires-Dist: getstream[webrtc]
Requires-Dist: kokoro>=0.9.4
Requires-Dist: misaki[en]>=0.9.4
Requires-Dist: numpy<2.3,>=2.2.6
